README.md
setup.py
bin/xmpro-demo-server
opc_app/OpenOPC.py
opc_app/__init__.py
opc_app/app.py
opc_app/config.py
opc_app/mylogger.py
opc_app.egg-info/PKG-INFO
opc_app.egg-info/SOURCES.txt
opc_app.egg-info/dependency_links.txt
opc_app.egg-info/requires.txt
opc_app.egg-info/top_level.txt