Metadata-Version: 2.1
Name: opc-app
Version: 1.0.0.0
Summary: API that communicates with KEP server for XMPro demo machine
Home-page: http://gitlab.icentralau.com.au/xmpro/opchttpgateway.git
Author: Kevin Glasson
Author-email: kevinglasson+icp_opc_add@gmail.com
License: UNKNOWN
Platform: UNKNOWN
Classifier: Development Status :: 3 - Alpha
Classifier: License :: OSI Approved :: MIT License
Classifier: Intended Audience :: Developers
Classifier: Programming Language :: Python :: 2.7
Requires-Python: >=2.7.*, <=3.0
